Metadata-Version: 2.1
Name: Probability-Distributions-LB
Version: 0.1.0
Summary: Gaussian and Binomial distributions
Home-page: UNKNOWN
License: UNKNOWN
Platform: UNKNOWN
License-File: license.txt
